peakpicker/__init__.py
peakpicker/max_intensity.py
peakpicker-0.0.1.dist-info/LICENSE.txt
peakpicker-0.0.1.dist-info/METADATA
peakpicker-0.0.1.dist-info/WHEEL
peakpicker-0.0.1.dist-info/top_level.txt
peakpicker-0.0.1.dist-info/RECORD
